odoo/addons/stock_location_is_sublocation/README.rst
odoo/addons/stock_location_is_sublocation/__init__.py
odoo/addons/stock_location_is_sublocation/__manifest__.py
odoo/addons/stock_location_is_sublocation/i18n/hr.po
odoo/addons/stock_location_is_sublocation/i18n/it.po
odoo/addons/stock_location_is_sublocation/i18n/stock_helper.pot
odoo/addons/stock_location_is_sublocation/i18n/stock_location_is_sublocation.pot
odoo/addons/stock_location_is_sublocation/models/__init__.py
odoo/addons/stock_location_is_sublocation/models/stock_location.py
odoo/addons/stock_location_is_sublocation/readme/CONTRIBUTORS.md
odoo/addons/stock_location_is_sublocation/readme/DESCRIPTION.md
odoo/addons/stock_location_is_sublocation/static/description/icon.png
odoo/addons/stock_location_is_sublocation/static/description/index.html
odoo/addons/stock_location_is_sublocation/tests/__init__.py
odoo/addons/stock_location_is_sublocation/tests/common.py
odoo/addons/stock_location_is_sublocation/tests/test_location_is_sublocation_of.py
odoo_addon_stock_location_is_sublocation-18.0.1.0.0.4.dist-info/METADATA
odoo_addon_stock_location_is_sublocation-18.0.1.0.0.4.dist-info/WHEEL
odoo_addon_stock_location_is_sublocation-18.0.1.0.0.4.dist-info/top_level.txt
odoo_addon_stock_location_is_sublocation-18.0.1.0.0.4.dist-info/RECORD
