Metadata-Version: 2.1
Name: odoo-addon-stock_location_is_sublocation
Version: 18.0.1.0.0.4
Requires-Python: >=3.10
Requires-Dist: odoo==18.0.*
Summary: Add method to check stock location is sublocation
Home-page: https://github.com/OCA/stock-logistics-warehouse
License: LGPL-3
Author: Camptocamp, ForgeFlow, Odoo Community Association (OCA)
Author-email: support@odoo-community.org
Classifier: Programming Language :: Python
Classifier: Framework :: Odoo
Classifier: Framework :: Odoo :: 18.0
Classifier: License :: OSI Approved :: GNU Lesser General Public License v3 (LGPLv3)
Classifier: Development Status :: 5 - Production/Stable
